# [Kingdom Hearts Birth By Sleep](../index.md) - Enums

## ATK_ATTR

| Enum       | Value      |
|------------|---------------|
| ATK_ATTR_NONE | 0 |
| ATK_ATTR_PHYSICAL | 1 |
| ATK_ATTR_FIRE | 2 |
| ATK_ATTR_ICE | 3 |
| ATK_ATTR_THUNDER | 4 |
| ATK_ATTR_DARK | 5 |
| ATK_ATTR_ZERO | 6 |
| ATK_ATTR_SPECIAL | 7 |
| ATK_ATTR_MAX | 8 |

## COMMAND_TYPE

| Enum       | Value      |
|------------|---------------|
| COMMAND_TYPE_NONE | 0 | ??? |
| COMMAND_TYPE_BASE | 1 | ??? |
| COMMAND_TYPE_DECK | 2 | ??? |
| COMMAND_TYPE_ACTION | 3 | ??? |
| COMMAND_TYPE_REACTION | 4 | ??? |
| COMMAND_TYPE_SHOOTLOCK | 5 | ??? |
| COMMAND_TYPE_STYLE | 6 | ??? |
| COMMAND_TYPE_DLINK | 7 | ??? |
| COMMAND_TYPE_ENCHANT | 8 | ??? |
| COMMAND_TYPE_ABILITY | 9 | ??? |
| COMMAND_TYPE_PRIZE | 10 | ??? |
| COMMAND_TYPE_OTHER | 11 | ??? |
| COMMAND_TYPE_ILLUSION | 12 | ??? |
| COMMAND_TYPE_END | 13 | ??? |

## COMMAND_KIND

| Enum       | Value      |
|------------|---------------|
| COMMAND_KIND_None | 0 | ??? |
| COMMAND_KIND_Attack | 1 | ??? |
| ENCHANT_MAX | 2 | ??? |
| COMMAND_KIND_Blitz01 | 2 | ??? |
| COMMAND_KIND_Blitz02 | 3 | ??? |
| COMMAND_KIND_Blitz03 | 4 | ??? |
| COMMAND_KIND_Blitz04 | 5 | ??? |
| COMMAND_KIND_Blitz05 | 6 | ??? |
| COMMAND_KIND_Blitz06 | 7 | ??? |
| COMMAND_KIND_Barrage07 | 8 | ??? |
| COMMAND_KIND_ACTION_REG_COUNTER | 8 | ??? |
| COMMAND_KIND_Barrage08 | 9 | ??? |
| COMMAND_KIND_Barrage09 | 10 | ??? |
| COMMAND_KIND_ACTION_REG_GUARD | 10 | ??? |
| COMMAND_KIND_Barrage10 | 11 | ??? |
| COMMAND_KIND_Barrage11 | 12 | ??? |
| COMMAND_KIND_Barrage12 | 13 | ??? |
| COMMAND_KIND_Barrage13 | 14 | ??? |
| COMMAND_KIND_Barrage14 | 15 | ??? |
| COMMAND_KIND_Combo15 | 16 | ??? |
| COMMAND_KIND_Finish | 17 | ??? |
| COMMAND_KIND_ACTION_REG_MOVE | 17 | ??? |
| COMMAND_KIND_LINK_SHIFT | 17 | ??? |
| COMMAND_KIND_FatalMode | 18 | ??? |
| COMMAND_KIND_SHOOT_REG | 18 | ??? |
| COMMAND_KIND_MagicWish | 19 | ??? |
| COMMAND_KIND_DECK_REG_FRIEND | 20 | ??? |
| COMMAND_KIND_SpeedRave | 20 | ??? |
| COMMAND_KIND_FireBlazer | 21 | ??? |
| COMMAND_KIND_DiamondDust | 22 | ??? |
| COMMAND_KIND_DECK_REG_ITEM | 23 | ??? |
| COMMAND_KIND_ThunderBolt | 23 | ??? |
| COMMAND_KIND_Cyclone | 24 | ??? |
| COMMAND_KIND_BladeCharge | 25 | ??? |
| COMMAND_KIND_SkyRider | 26 | ??? |
| COMMAND_KIND_RockBreaker | 27 | ??? |
| COMMAND_KIND_GhostDrive | 28 | ??? |
| COMMAND_KIND_RhythmMixer | 29 | ??? |
| COMMAND_KIND_DarkImpulse | 30 | ??? |
| COMMAND_KIND_WingBlade | 31 | ??? |
| COMMAND_KIND_IceBlast | 32 | ??? |
| COMMAND_KIND_DLink1 | 33 | ??? |
| COMMAND_KIND_DLink2 | 34 | ??? |
| COMMAND_KIND_DLink3 | 35 | ??? |
| COMMAND_KIND_ACTION_REG | 35 | ??? |
| COMMAND_KIND_DLink4 | 36 | ??? |
| COMMAND_KIND_DLink5 | 37 | ??? |
| COMMAND_KIND_DLink6 | 38 | ??? |
| COMMAND_KIND_DLink7 | 39 | ??? |
| COMMAND_KIND_DECK_REG_ATTACK | 40 | ??? |
| COMMAND_KIND_DLink8 | 40 | ??? |
| COMMAND_KIND_DLink9 | 41 | ??? |
| COMMAND_KIND_DLink10 | 42 | ??? |
| COMMAND_KIND_DLink11 | 43 | ??? |
| COMMAND_KIND_DLink12 | 44 | ??? |
| COMMAND_KIND_DLink13 | 45 | ??? |
| COMMAND_KIND_Combo17 | 46 | ??? |
| COMMAND_KIND_DLink17 | 47 | ??? |
| COMMAND_KIND_DLink1R | 48 | ??? |
| COMMAND_KIND_DLink2R | 49 | ??? |
| COMMAND_KIND_DLink3R | 50 | ??? |
| COMMAND_KIND_DLink4R | 51 | ??? |
| COMMAND_KIND_DLink5R | 52 | ??? |
| COMMAND_KIND_DLink6R | 53 | ??? |
| COMMAND_KIND_DLink7R | 54 | ??? |
| COMMAND_KIND_DLink8R | 55 | ??? |
| COMMAND_KIND_DLink9R | 56 | ??? |
| COMMAND_KIND_DECK_REG_MAGIC | 57 | ??? |
| COMMAND_KIND_DLink10R | 57 | ??? |
| COMMAND_KIND_DLink11R | 58 | ??? |
| COMMAND_KIND_DLink12R | 59 | ??? |
| COMMAND_KIND_DLink13R | 60 | ??? |
| COMMAND_KIND_FinishV01 | 61 | ??? |
| COMMAND_KIND_FinishA02 | 62 | ??? |
| COMMAND_KIND_FinishT03 | 63 | ??? |
| COMMAND_KIND_FinishV11 | 64 | ??? |
| COMMAND_KIND_FinishA12 | 65 | ??? |
| COMMAND_KIND_FinishT13 | 66 | ??? |
| COMMAND_KIND_FinishC14 | 67 | ??? |
| COMMAND_KIND_FinishC15 | 68 | ??? |
| COMMAND_KIND_FinishV21 | 69 | ??? |
| COMMAND_KIND_FinishA22 | 70 | ??? |
| COMMAND_KIND_FinishT23 | 71 | ??? |
| COMMAND_KIND_FinishC24 | 72 | ??? |
| COMMAND_KIND_FinishC25 | 73 | ??? |
| COMMAND_KIND_FinishC26 | 74 | ??? |
| COMMAND_KIND_FinishC27 | 75 | ??? |
| COMMAND_KIND_FinishV31 | 76 | ??? |
| COMMAND_KIND_FinishA32 | 77 | ??? |
| COMMAND_KIND_FinishT33 | 78 | ??? |
| COMMAND_KIND_FinishC34 | 79 | ??? |
| COMMAND_KIND_FinishC35 | 80 | ??? |
| COMMAND_KIND_FinishC36 | 81 | ??? |
| COMMAND_KIND_FinishV41 | 82 | ??? |
| COMMAND_KIND_FinishA42 | 83 | ??? |
| COMMAND_KIND_FinishT43 | 84 | ??? |
| COMMAND_KIND_FinishC44 | 85 | ??? |
| COMMAND_KIND_FinishC45 | 86 | ??? |
| COMMAND_KIND_FinishC46 | 87 | ??? |
| COMMAND_KIND_FinishV51 | 88 | ??? |
| COMMAND_KIND_FinishA52 | 89 | ??? |
| COMMAND_KIND_FinishT53 | 90 | ??? |
| COMMAND_KIND_AerialBreak | 91 | ??? |
| COMMAND_KIND_DECK_START | 91 | ??? |
| COMMAND_KIND_FinalBreak | 92 | ??? |
| COMMAND_KIND_CosmicArts | 93 | ??? |
| COMMAND_KIND_Catastrophe | 94 | ??? |
| COMMAND_KIND_Rush | 95 | ??? |
| COMMAND_KIND_FireRush | 96 | ??? |
| COMMAND_KIND_DarkCatalyst | 97 | ??? |
| COMMAND_KIND_SonicRave | 98 | ??? |
| COMMAND_KIND_Vengeance | 99 | ??? |
| COMMAND_KIND_Zantetsuken | 100 | ??? |
| COMMAND_KIND_StrikeRaid | 101 | ??? |
| COMMAND_KIND_FreezeRaid | 102 | ??? |
| COMMAND_KIND_TreasureRaid | 103 | ??? |
| COMMAND_KIND_ReflectRaid | 104 | ??? |
| COMMAND_KIND_Judgement | 105 | ??? |
| COMMAND_KIND_FireBlitz | 106 | ??? |
| COMMAND_KIND_ReflectBlitz | 107 | ??? |
| COMMAND_KIND_ThunderBlitz | 108 | ??? |
| COMMAND_KIND_AerialSlam | 109 | ??? |
| COMMAND_KIND_Midareuchi | 110 | ??? |
| COMMAND_KIND_LastArcanum | 111 | ??? |
| COMMAND_KIND_TimeSplicer | 112 | ??? |
| COMMAND_KIND_PoisonBlade | 113 | ??? |
| COMMAND_KIND_WishBlade | 114 | ??? |
| COMMAND_KIND_BlizzardBlade | 115 | ??? |
| COMMAND_KIND_StunBlade | 116 | ??? |
| COMMAND_KIND_SlotBlade | 117 | ??? |
| COMMAND_KIND_FireStrike | 118 | ??? |
| COMMAND_KIND_ConfuseStrike | 119 | ??? |
| COMMAND_KIND_BindStrike | 120 | ??? |
| COMMAND_KIND_TornadoStrike | 121 | ??? |
| COMMAND_KIND_BrutalForce | 122 | ??? |
| COMMAND_KIND_MagneSpiral | 123 | ??? |
| COMMAND_KIND_Salvation | 124 | ??? |
| COMMAND_KIND_Kamaitachi | 125 | ??? |
| COMMAND_KIND_Kishikaisei | 126 | ??? |
| COMMAND_KIND_MagneBreaker | 127 | ??? |
| COMMAND_KIND_GaiaImpact | 128 | ??? |
| COMMAND_KIND_Sutemi | 129 | ??? |
| COMMAND_KIND_BreakTime | 130 | ??? |
| COMMAND_KIND_Fire | 131 | ??? |
| COMMAND_KIND_Fira | 132 | ??? |
| COMMAND_KIND_Firaga | 133 | ??? |
| COMMAND_KIND_DarkFiraga | 134 | ??? |
| COMMAND_KIND_FiragaStorm | 135 | ??? |
| COMMAND_KIND_TripleFiraga | 136 | ??? |
| COMMAND_KIND_SlowFiraga | 137 | ??? |
| COMMAND_KIND_Blizzard | 138 | ??? |
| COMMAND_KIND_Blizzara | 139 | ??? |
| COMMAND_KIND_Blizzaga | 140 | ??? |
| COMMAND_KIND_DECK_REG | 140 | ??? |
| COMMAND_KIND_TripleBlizzaga | 141 | ??? |
| COMMAND_KIND_Thunder | 142 | ??? |
| COMMAND_KIND_Thundra | 143 | ??? |
| COMMAND_KIND_Thundaga | 144 | ??? |
| COMMAND_KIND_ThundagaShot | 145 | ??? |
| COMMAND_KIND_Cure | 146 | ??? |
| COMMAND_KIND_Cura | 147 | ??? |
| COMMAND_KIND_Curaga | 148 | ??? |
| COMMAND_KIND_Esuna | 149 | ??? |
| COMMAND_KIND_DetoneShield | 150 | ??? |
| COMMAND_KIND_DetoneSquare | 151 | ??? |
| COMMAND_KIND_DetoneChaser | 152 | ??? |
| COMMAND_KIND_ZeroGravity | 153 | ??? |
| COMMAND_KIND_ZeroGravira | 154 | ??? |
| COMMAND_KIND_ZeroGraviga | 155 | ??? |
| COMMAND_KIND_Magne | 156 | ??? |
| COMMAND_KIND_Magnera | 157 | ??? |
| COMMAND_KIND_Magnega | 158 | ??? |
| COMMAND_KIND_MunnyMagne | 159 | ??? |
| COMMAND_KIND_HpMagne | 160 | ??? |
| COMMAND_KIND_FocusMagne | 161 | ??? |
| COMMAND_KIND_Aero | 162 | ??? |
| COMMAND_KIND_Aera | 163 | ??? |
| COMMAND_KIND_Aeroga | 164 | ??? |
| COMMAND_KIND_Degenerate | 165 | ??? |
| COMMAND_KIND_Holy | 166 | ??? |
| COMMAND_KIND_Freeze | 167 | ??? |
| COMMAND_KIND_GlacialArts | 168 | ??? |
| COMMAND_KIND_IceBarrage | 169 | ??? |
| COMMAND_KIND_FiragaBurst | 170 | ??? |
| COMMAND_KIND_RagingStorm | 171 | ??? |
| COMMAND_KIND_MegaFlare | 172 | ??? |
| COMMAND_KIND_Quake | 173 | ??? |
| COMMAND_KIND_Tornado | 174 | ??? |
| COMMAND_KIND_Meteor | 175 | ??? |
| COMMAND_KIND_Transcendence | 176 | ??? |
| COMMAND_KIND_Minimum | 177 | ??? |
| COMMAND_KIND_BlackOut | 178 | ??? |
| COMMAND_KIND_FiragaSpark | 179 | ??? |
| COMMAND_KIND_Confuse | 180 | ??? |
| COMMAND_KIND_Bind | 181 | ??? |
| COMMAND_KIND_Poison | 182 | ??? |
| COMMAND_KIND_Slow | 183 | ??? |
| COMMAND_KIND_Stop | 184 | ??? |
| COMMAND_KIND_Stopra | 185 | ??? |
| COMMAND_KIND_Stopga | 186 | ??? |
| COMMAND_KIND_Sleple | 187 | ??? |
| COMMAND_KIND_Potion | 188 | ??? |
| COMMAND_KIND_HiPotion | 189 | ??? |
| COMMAND_KIND_MegePotion | 190 | ??? |
| COMMAND_KIND_Ether | 191 | ??? |
| COMMAND_KIND_MegaEther | 192 | ??? |
| COMMAND_KIND_Remedy | 193 | ??? |
| COMMAND_KIND_Elixir | 194 | ??? |
| COMMAND_KIND_LastElixir | 195 | ??? |
| COMMAND_KIND_BalloonLetter | 196 | ??? |
| COMMAND_KIND_DECK_ICE_START | 197 | ??? |
| COMMAND_KIND_Ice1 | 197 | ??? |
| COMMAND_KIND_Ice2 | 198 | ??? |
| COMMAND_KIND_Ice3 | 199 | ??? |
| COMMAND_KIND_Ice4 | 200 | ??? |
| COMMAND_KIND_Ice5 | 201 | ??? |
| COMMAND_KIND_Ice6 | 202 | ??? |
| COMMAND_KIND_Ice7 | 203 | ??? |
| COMMAND_KIND_Ice8 | 204 | ??? |
| COMMAND_KIND_Ice9 | 205 | ??? |
| COMMAND_KIND_Ice10 | 206 | ??? |
| COMMAND_KIND_Ice11 | 207 | ??? |
| COMMAND_KIND_Ice12 | 208 | ??? |
| COMMAND_KIND_Ice13 | 209 | ??? |
| COMMAND_KIND_Ice14 | 210 | ??? |
| COMMAND_KIND_DECK_ICE_END | 211 | ??? |
| COMMAND_KIND_FriendCure | 211 | ??? |
| COMMAND_KIND_FriendCura | 212 | ??? |
| COMMAND_KIND_FriendCuraga | 213 | ??? |
| COMMAND_KIND_FriendEsuna | 214 | ??? |
| COMMAND_KIND_Confetti | 215 | ??? |
| COMMAND_KIND_Cracker | 216 | ??? |
| COMMAND_KIND_Provoke | 217 | ??? |
| COMMAND_KIND_GutsPose | 218 | ??? |
| COMMAND_KIND_DeckScramble | 219 | ??? |
| COMMAND_KIND_Banish | 220 | ??? |
| COMMAND_KIND_RagingCharge | 221 | ??? |
| COMMAND_KIND_Voltage | 222 | ??? |
| COMMAND_KIND_TrinityLimit | 223 | ??? |
| COMMAND_KIND_Gold | 224 | ??? |
| COMMAND_KIND_Black | 225 | ??? |
| COMMAND_KIND_DeckFinish | 226 | ??? |
| COMMAND_KIND_DeckDarkVolley | 227 | ??? |
| COMMAND_KIND_HolyStorm | 228 | ??? |
| COMMAND_KIND_WishTurn | 229 | ??? |
| COMMAND_KIND_FairyStep | 230 | ??? |
| COMMAND_KIND_WishShot | 231 | ??? |
| COMMAND_KIND_FairyCure | 232 | ??? |
| COMMAND_KIND_DwarfDoc | 233 | ??? |
| COMMAND_KIND_DwarfGrumpy | 234 | ??? |
| COMMAND_KIND_DwarfSneezy | 235 | ??? |
| COMMAND_KIND_DwarfHappy | 236 | ??? |
| COMMAND_KIND_DwarfSleepy | 237 | ??? |
| COMMAND_KIND_DwarfBashful | 238 | ??? |
| COMMAND_KIND_DwarfDopey | 239 | ??? |
| COMMAND_KIND_DarkAxis | 240 | ??? |
| COMMAND_KIND_DarkSplicer | 241 | ??? |
| COMMAND_KIND_Illusion1 | 242 | ??? |
| COMMAND_KIND_Illusion2 | 243 | ??? |
| COMMAND_KIND_Illusion3 | 244 | ??? |
| COMMAND_KIND_Illusion4 | 245 | ??? |
| COMMAND_KIND_Illusion5 | 246 | ??? |
| COMMAND_KIND_DECK_END | 247 | ??? |
| COMMAND_KIND_DeckEnd | 247 | ??? |
| COMMAND_KIND_MOVE_START | 248 | ??? |
| COMMAND_KIND_Slide | 248 | ??? |
| COMMAND_KIND_Jump | 249 | ??? |
| COMMAND_KIND_HiJump | 250 | ??? |
| COMMAND_KIND_DodgeRoll | 251 | ??? |
| COMMAND_KIND_ThunderRoll | 252 | ??? |
| COMMAND_KIND_QuickRoll | 253 | ??? |
| COMMAND_KIND_FireRoll | 254 | ??? |
| COMMAND_KIND_AirSlide | 255 | ??? |
| COMMAND_KIND_IceSlide | 256 | ??? |
| COMMAND_KIND_SlideTurn | 257 | ??? |
| COMMAND_KIND_Glide | 258 | ??? |
| COMMAND_KIND_SuperGlide | 259 | ??? |
| COMMAND_KIND_FireGlide | 260 | ??? |
| COMMAND_KIND_HomingSlide | 261 | ??? |
| COMMAND_KIND_Tereport | 262 | ??? |
| COMMAND_KIND_SonicImpact | 263 | ??? |
| COMMAND_KIND_SkyVault | 264 | ??? |
| COMMAND_KIND_Guard | 265 | ??? |
| COMMAND_KIND_HealGuard | 266 | ??? |
| COMMAND_KIND_FocusGuard | 267 | ??? |
| COMMAND_KIND_ShockGuard | 268 | ??? |
| COMMAND_KIND_PoisonGuard | 269 | ??? |
| COMMAND_KIND_Reflect | 270 | ??? |
| COMMAND_KIND_HealReflect | 271 | ??? |
| COMMAND_KIND_FocusReflect | 272 | ??? |
| COMMAND_KIND_ConfuseReflect | 273 | ??? |
| COMMAND_KIND_StopReflect | 274 | ??? |
| COMMAND_KIND_GuardSlash | 275 | ??? |
| COMMAND_KIND_GuardImpact | 276 | ??? |
| COMMAND_KIND_BackBreaker | 277 | ??? |
| COMMAND_KIND_ReflectPulse | 278 | ??? |
| COMMAND_KIND_CounterRaid | 279 | ??? |
| COMMAND_KIND_CounterBlitz | 280 | ??? |
| COMMAND_KIND_CounterCharge | 281 | ??? |
| COMMAND_KIND_AirRecovery | 282 | ??? |
| COMMAND_KIND_MOVE_END | 283 | ??? |
| COMMAND_KIND_SHOOT_START | 283 | ??? |
| COMMAND_KIND_ShootLock | 283 | ??? |
| COMMAND_KIND_StarBurst | 284 | ??? |
| COMMAND_KIND_FlameSpark | 285 | ??? |
| COMMAND_KIND_ChaosGunner | 286 | ??? |
| COMMAND_KIND_BubbleBlaster | 287 | ??? |
| COMMAND_KIND_DarkVolley | 288 | ??? |
| COMMAND_KIND_Ragnarock | 289 | ??? |
| COMMAND_KIND_StormShock | 290 | ??? |
| COMMAND_KIND_BioBarrage | 291 | ??? |
| COMMAND_KIND_RainbowShower | 292 | ??? |
| COMMAND_KIND_PsychicsPulse | 293 | ??? |
| COMMAND_KIND_PhotonCharge | 294 | ??? |
| COMMAND_KIND_IceSlider | 295 | ??? |
| COMMAND_KIND_WarpDrive | 296 | ??? |
| COMMAND_KIND_ShadowRunner | 297 | ??? |
| COMMAND_KIND_DarkCannon | 298 | ??? |
| COMMAND_KIND_UltimaCannon | 299 | ??? |
| COMMAND_KIND_ShinyBloom | 300 | ??? |
| COMMAND_KIND_BladeBallista | 301 | ??? |
| COMMAND_KIND_SHOOT_END | 302 | ??? |
| COMMAND_KIND_Save | 302 | ??? |
| COMMAND_KIND_Talk | 303 | ??? |
| COMMAND_KIND_Open | 304 | ??? |
| COMMAND_KIND_Check | 305 | ??? |
| COMMAND_KIND_Shop | 306 | ??? |
| COMMAND_KIND_action5 | 307 | ??? |
| COMMAND_KIND_Cover | 308 | ??? |
| COMMAND_KIND_Goto | 309 | ??? |
| COMMAND_KIND_Goal | 310 | ??? |
| COMMAND_KIND_Call | 311 | ??? |
| COMMAND_KIND_LastDance | 312 | ??? |
| COMMAND_KIND_BraveRescue | 313 | ??? |
| COMMAND_KIND_BraveRevenge | 314 | ??? |
| COMMAND_KIND_BraveSlash | 315 | ??? |
| COMMAND_KIND_WhiteSilence | 316 | ??? |
| COMMAND_KIND_BoulderBreaker | 317 | ??? |
| COMMAND_KIND_SwingSlash | 318 | ??? |
| COMMAND_KIND_StitchShoot | 319 | ??? |
| COMMAND_KIND_StitchStrike | 320 | ??? |
| COMMAND_KIND_HolyFlood | 321 | ??? |
| COMMAND_KIND_DualLimit | 322 | ??? |
| COMMAND_KIND_HangOn | 323 | ??? |
| COMMAND_KIND_PunishKitty | 324 | ??? |
| COMMAND_KIND_FairyMagic | 325 | ??? |
| COMMAND_KIND_TurnOver | 326 | ??? |
| COMMAND_KIND_action25 | 327 | ??? |
| COMMAND_KIND_action26 | 328 | ??? |
| COMMAND_KIND_HealLight | 329 | ??? |
| COMMAND_KIND_NetAccess | 330 | ??? |
| COMMAND_KIND_NetWarp | 331 | ??? |
| COMMAND_KIND_NetReady | 332 | ??? |
| COMMAND_KIND_NetCancel | 333 | ??? |
| COMMAND_KIND_NetExchange | 334 | ??? |
| COMMAND_KIND_NetStart | 335 | ??? |
| COMMAND_KIND_DebugJump | 336 | ??? |
| COMMAND_KIND_COMMAND_MAX | 337 | ??? |
| COMMAND_KIND_STYLE_START | 337 | ??? |
| COMMAND_KIND_StyleNormal | 337 | ??? |
| COMMAND_KIND_StyleFatalMode | 338 | ??? |
| COMMAND_KIND_StyleMagicWish | 339 | ??? |
| COMMAND_KIND_StyleSpeedRave | 340 | ??? |
| COMMAND_KIND_StyleFireBlazer | 341 | ??? |
| COMMAND_KIND_StyleDiamondDust | 342 | ??? |
| COMMAND_KIND_StyleThunderBolt | 343 | ??? |
| COMMAND_KIND_StyleCyclone | 344 | ??? |
| COMMAND_KIND_StyleBladeCharge | 345 | ??? |
| COMMAND_KIND_StyleSkyRider | 346 | ??? |
| COMMAND_KIND_StyleRockBreaker | 347 | ??? |
| COMMAND_KIND_StyleGhostDrive | 348 | ??? |
| COMMAND_KIND_StyleRhythmMixer | 349 | ??? |
| COMMAND_KIND_StyleDarkImpulse | 350 | ??? |
| COMMAND_KIND_StyleWingBlade | 351 | ??? |
| COMMAND_KIND_StyleIceBlast | 352 | ??? |
| COMMAND_KIND_STYLE_END | 353 | ??? |
| COMMAND_KIND_StyleEnd | 353 | ??? |
| COMMAND_KIND_LINK_START | 354 | ??? |
| COMMAND_KIND_LinkNull | 354 | ??? |
| COMMAND_KIND_LinkKing | 355 | ??? |
| COMMAND_KIND_LinkDonald | 356 | ??? |
| COMMAND_KIND_LinkGoofy | 357 | ??? |
| COMMAND_KIND_LinkStitch | 358 | ??? |
| COMMAND_KIND_LinkPan | 359 | ??? |
| COMMAND_KIND_LinkMaleficent | 360 | ??? |
| COMMAND_KIND_LinkCinderella | 361 | ??? |
| COMMAND_KIND_LinkSnowWhite | 362 | ??? |
| COMMAND_KIND_LinkZack | 363 | ??? |
| COMMAND_KIND_LinkPete | 364 | ??? |
| COMMAND_KIND_LinkAqua | 365 | ??? |
| COMMAND_KIND_LinkVentus | 366 | ??? |
| COMMAND_KIND_LinkTerra | 367 | ??? |
| COMMAND_KIND_LinkArmoredAqua | 368 | ??? |
| COMMAND_KIND_LinkArmoredVentus | 369 | ??? |
| COMMAND_KIND_LinkArmoredTerra | 370 | ??? |
| COMMAND_KIND_LinkVanitas | 371 | ??? |
| COMMAND_KIND_LinkKingR | 372 | ??? |
| COMMAND_KIND_LinkDonaldR | 373 | ??? |
| COMMAND_KIND_LinkGoofyR | 374 | ??? |
| COMMAND_KIND_LinkStitchR | 375 | ??? |
| COMMAND_KIND_LinkPanR | 376 | ??? |
| COMMAND_KIND_LinkMaleficentR | 377 | ??? |
| COMMAND_KIND_LinkCinderellaR | 378 | ??? |
| COMMAND_KIND_LinkSnowWhiteR | 379 | ??? |
| COMMAND_KIND_LinkZackR | 380 | ??? |
| COMMAND_KIND_LinkPeteR | 381 | ??? |
| COMMAND_KIND_LinkAquaR | 382 | ??? |
| COMMAND_KIND_LinkVentusR | 383 | ??? |
| COMMAND_KIND_LinkTerraR | 384 | ??? |
| COMMAND_KIND_LinkPC1 | 385 | ??? |
| COMMAND_KIND_LinkPC2 | 386 | ??? |
| COMMAND_KIND_LinkPC3 | 387 | ??? |
| COMMAND_KIND_LinkPC4 | 388 | ??? |
| COMMAND_KIND_LinkPC5 | 389 | ??? |
| COMMAND_KIND_LinkPC6 | 390 | ??? |
| COMMAND_KIND_LinkPC7 | 391 | ??? |
| COMMAND_KIND_LinkPC8 | 392 | ??? |
| COMMAND_KIND_LinkEnd | 393 | ??? |
| COMMAND_KIND_ILLUSION_START | 394 | ??? |
| COMMAND_KIND_LINK_END | 394 | ??? |
| COMMAND_KIND_IllusionNull | 394 | ??? |
| COMMAND_KIND_IllusionTypeM | 395 | ??? |
| COMMAND_KIND_IllusionTypeS | 396 | ??? |
| COMMAND_KIND_IllusionTypeB | 397 | ??? |
| COMMAND_KIND_IllusionTypeP | 398 | ??? |
| COMMAND_KIND_IllusionTypeI | 399 | ??? |
| COMMAND_KIND_ILLUSION_END | 400 | ??? |
| COMMAND_KIND_IllusionEnd | 400 | ??? |
| COMMAND_KIND_IllusionAttack1 | 401 | ??? |
| COMMAND_KIND_IllusionAttack2 | 402 | ??? |
| COMMAND_KIND_IllusionAttack3 | 403 | ??? |
| COMMAND_KIND_IllusionAttack4 | 404 | ??? |
| COMMAND_KIND_IllusionAttack5 | 405 | ??? |
| COMMAND_KIND_IllusionFinish1 | 406 | ??? |
| COMMAND_KIND_IllusionFinish2 | 407 | ??? |
| COMMAND_KIND_IllusionFinish3 | 408 | ??? |
| COMMAND_KIND_IllusionFinish4 | 409 | ??? |
| COMMAND_KIND_IllusionFinish5 | 410 | ??? |
| COMMAND_KIND_IllusionDeck1 | 411 | ??? |
| COMMAND_KIND_IllusionDeck2 | 412 | ??? |
| COMMAND_KIND_IllusionDeck3 | 413 | ??? |
| COMMAND_KIND_IllusionDeck4 | 414 | ??? |
| COMMAND_KIND_IllusionDeck5 | 415 | ??? |
| COMMAND_KIND_IllusionAction1 | 416 | ??? |
| COMMAND_KIND_IllusionAction2 | 417 | ??? |
| COMMAND_KIND_IllusionAction3 | 418 | ??? |
| COMMAND_KIND_IllusionAction4 | 419 | ??? |
| COMMAND_KIND_IllusionAction5 | 420 | ??? |
| COMMAND_KIND_ENCHANT_START | 421 | ??? |
| ENCHANT_KIND_None | 421 | ??? |
| ENCHANT_KIND_QuickReload | 422 | ??? |
| ENCHANT_KIND_Haste | 423 | ??? |
| ENCHANT_KIND_Protect | 424 | ??? |
| ENCHANT_KIND_Shell | 425 | ??? |
| ENCHANT_KIND_AttackUp | 426 | ??? |
| ENCHANT_KIND_MagicUp | 427 | ??? |
| ENCHANT_KIND_Regeneration | 428 | ??? |
| ENCHANT_KIND_MunnyUp | 429 | ??? |
| ENCHANT_KIND_Berserk | 430 | ??? |
| ENCHANT_KIND_MagicBarrier | 431 | ??? |
| ENCHANT_KIND_AttackBarrier | 432 | ??? |
| ENCHANT_KIND_Levitate | 433 | ??? |
| ENCHANT_KIND_Reraise | 434 | ??? |
| ENCHANT_KIND_AutoTeleport | 435 | ??? |
| ENCHANT_KIND_AutoRecovery | 436 | ??? |
| ENCHANT_KIND_Steal | 437 | ??? |
| ENCHANT_KIND_Drain | 438 | ??? |
| ENCHANT_KIND_DoubleHit | 439 | ??? |
| ENCHANT_KIND_ShootRave | 440 | ??? |
| ENCHANT_KIND_OverDrive | 441 | ??? |
| ENCHANT_KIND_BurnStrike | 442 | ??? |
| ENCHANT_KIND_GaugeBoost | 443 | ??? |
| ENCHANT_KIND_AutoCounter | 444 | ??? |
| ENCHANT_KIND_StunStrike | 445 | ??? |
| ENCHANT_KIND_EXPx2 | 446 | ??? |
| ENCHANT_KIND_CPx2 | 447 | ??? |
| ENCHANT_KIND_AutoGuard | 448 | ??? |
| ENCHANT_KIND_Unknown | 449 | ??? |
| COMMAND_KIND_ENCHANT_END | 450 | ??? |
| ENCHANT_KIND_Random | 450 | ??? |
| ABILITY_KIND_None | 451 | ??? |
| COMMAND_KIND_ABILITY_START | 451 | ??? |
| ABILITY_KIND_Draw | 452 | ??? |
| ABILITY_KIND_HpPrizeUp | 453 | ??? |
| ABILITY_KIND_FpPrizeUp | 454 | ??? |
| ABILITY_KIND_LuckUp | 455 | ??? |
| ABILITY_KIND_HpUp | 456 | ??? |
| ABILITY_KIND_Exp0 | 457 | ??? |
| ABILITY_KIND_FireUp | 458 | ??? |
| ABILITY_KIND_BlizzardUp | 459 | ??? |
| ABILITY_KIND_ThunderUp | 460 | ??? |
| ABILITY_KIND_CureUp | 461 | ??? |
| ABILITY_KIND_ItemUp | 462 | ??? |
| ABILITY_KIND_AttackHaste | 463 | ??? |
| ABILITY_KIND_MagicHaste | 464 | ??? |
| ABILITY_KIND_FinishUp | 465 | ??? |
| ABILITY_KIND_SFinishUp | 466 | ??? |
| ABILITY_KIND_ComboPlus | 467 | ??? |
| ABILITY_KIND_AirComboPlus | 468 | ??? |
| ABILITY_KIND_FireGuard | 469 | ??? |
| ABILITY_KIND_BlizzardGuard | 470 | ??? |
| ABILITY_KIND_ThunderGuard | 471 | ??? |
| ABILITY_KIND_DarkGuard | 472 | ??? |
| ABILITY_KIND_ReloadBoost | 473 | ??? |
| ABILITY_KIND_Defender | 474 | ??? |
| ABILITY_KIND_ExpChance | 475 | ??? |
| ABILITY_KIND_WalkingExp | 476 | ??? |
| ABILITY_KIND_DamageAspir | 477 | ??? |
| ABILITY_KIND_LastLeave | 478 | ??? |
| ABILITY_KIND_ComboLeave | 479 | ??? |
| ABILITY_KIND_Libra | 480 | ??? |
| ABILITY_KIND_LeafVeil | 481 | ??? |
| COMMAND_KIND_PRIZE_START | 482 | ??? |
| COMMAND_KIND_ABILITY_END | 482 | ??? |
| PRIZE_KIND_HpPrizeS | 482 | ??? |
| PRIZE_KIND_HpPrizeL | 483 | ??? |
| PRIZE_KIND_FpPrizeS | 484 | ??? |
| PRIZE_KIND_FpPrizeL | 485 | ??? |
| PRIZE_KIND_MunnyPrizeS | 486 | ??? |
| PRIZE_KIND_MunnyPrizeM | 487 | ??? |
| PRIZE_KIND_MunnyPrizeL | 488 | ??? |
| PRIZE_KIND_PrizeBoxAS | 489 | ??? |
| PRIZE_KIND_PrizeBoxAM | 490 | ??? |
| PRIZE_KIND_PrizeBoxAL | 491 | ??? |
| PRIZE_KIND_PrizeBoxB | 492 | ??? |
| PRIZE_KIND_PrizeBoxC | 493 | ??? |
| PRIZE_KIND_PrizeBoxD | 494 | ??? |
| PRIZE_KIND_BattleDicePrize | 495 | ??? |
| PRIZE_KIND_DLinkPrize | 496 | ??? |
| COMMAND_KIND_PRIZE_END | 497 | ??? |
| PRIZE_KIND_prize16 | 497 | ??? |
| COMMAND_KIND_End | 498 | ??? |

## WORLD_ID

| Enum       | Value      | Description      |
|------------|---------------|---------------|
| WORLD_ID_EX | 0 | (Generic) |
| WORLD_ID_DP | 1 | Land of Departure |
| WORLD_ID_SW | 2 | Dwarf Woodlands |
| WORLD_ID_CD | 3 | Castle of Dreams |
| WORLD_ID_SB | 4 | Enchanted Domain |
| WORLD_ID_YT | 5 | Mysterious Tower |
| WORLD_ID_RG | 6 | Radiant Garden |
| WORLD_ID_JB | 7 | Jungle Book (JP version) / Dark World (FM version) |
| WORLD_ID_HE | 8 | Olympus Coliseum |
| WORLD_ID_LS | 9 | Deep Space |
| WORLD_ID_DI | 10 | Destiny Island |
| WORLD_ID_PP | 11 | Never Land |
| WORLD_ID_DC | 12 | Disney Town |
| WORLD_ID_KG | 13 | Keyblade Graveyard |
| WORLD_ID_14 | 14 | ??? |
| _WORLD_ID_STAGEMAX | 14 | ??? |
| WORLD_ID_VS | 15 | Mirage Arena |
| WORLD_ID_BD | 16 | Command Board |
| WORLD_ID_WM | 17 | World Map |
| WORLD_ID_WP | 18 | World Path |
| WORLD_ID_19 | 19 | ??? |
| _WORLD_ID_VALIDMAX | 19 | ??? |
| WORLD_ID_20 | 20 | ??? |
| WORLD_ID_21 | 21 | ??? |
| WORLD_ID_22 | 22 | ??? |
| WORLD_ID_JF | 23 | Jump Festa |
| _WORLD_ID_MAX | 24 | ??? |
| _WORLD_ID_RESTART | 128 | ??? |
| _WORLD_ID_ENDING | 129 | ??? |
| _WORLD_ID_THEATER_END | 130 | ??? |

## ITEM_ID

| Enum       | Value      | Description      |
|------------|---------------|---------------|
| DUMMY | 0 | ??? |
| WEP_KEY_BLADE_VE_0 | 1 | ??? |
| WEP_KEY_BLADE_VE_1 | 2 | ??? |
| WEP_KEY_BLADE_VE_2 | 3 | ??? |
| WEP_KEY_BLADE_VE_3 | 4 | ??? |
| WEP_KEY_BLADE_VE_4 | 5 | ??? |
| WEP_KEY_BLADE_VE_5 | 6 | ??? |
| WEP_KEY_BLADE_VE_6 | 7 | ??? |
| WEP_KEY_BLADE_VE_7 | 8 | ??? |
| WEP_KEY_BLADE_VE_8 | 9 | ??? |
| WEP_KEY_BLADE_VE_9 | 10 | ??? |
| WEP_KEY_BLADE_VE_10 | 11 | ??? |
| WEP_KEY_BLADE_VE_12 | 13 | ??? |
| WEP_KEY_BLADE_VE_13 | 14 | ??? |
| WEP_KEY_BLADE_VE_14 | 16 | ??? |
| WEP_KEY_BLADE_VE_15 | 17 | ??? |
| WEP_KEY_BLADE_VE_16 | 18 | ??? |
| WEP_KEY_BLADE_TE_0 | 256 | ??? |
| WEP_KEY_BLADE_TE_1 | 257 | ??? |
| WEP_KEY_BLADE_TE_2 | 258 | ??? |
| WEP_KEY_BLADE_TE_3 | 259 | ??? |
| WEP_KEY_BLADE_TE_4 | 260 | ??? |
| WEP_KEY_BLADE_TE_5 | 261 | ??? |
| WEP_KEY_BLADE_TE_6 | 262 | ??? |
| WEP_KEY_BLADE_TE_7 | 263 | ??? |
| WEP_KEY_BLADE_TE_8 | 264 | ??? |
| WEP_KEY_BLADE_TE_9 | 265 | ??? |
| WEP_KEY_BLADE_TE_10 | 266 | ??? |
| WEP_KEY_BLADE_TE_11 | 267 | ??? |
| WEP_KEY_BLADE_TE_12 | 268 | ??? |
| WEP_KEY_BLADE_TE_14 | 272 | ??? |
| WEP_KEY_BLADE_TE_15 | 273 | ??? |
| WEP_KEY_BLADE_TE_16 | 274 | ??? |
| WEP_KEY_BLADE_AQ_0 | 512 | ??? |
| WEP_KEY_BLADE_AQ_1 | 513 | ??? |
| WEP_KEY_BLADE_AQ_2 | 514 | ??? |
| WEP_KEY_BLADE_AQ_3 | 515 | ??? |
| WEP_KEY_BLADE_AQ_4 | 516 | ??? |
| WEP_KEY_BLADE_AQ_5 | 517 | ??? |
| WEP_KEY_BLADE_AQ_6 | 518 | ??? |
| WEP_KEY_BLADE_AQ_7 | 519 | ??? |
| WEP_KEY_BLADE_AQ_8 | 520 | ??? |
| WEP_KEY_BLADE_AQ_9 | 521 | ??? |
| WEP_KEY_BLADE_AQ_10 | 522 | ??? |
| WEP_KEY_BLADE_AQ_11 | 523 | ??? |
| WEP_KEY_BLADE_AQ_12 | 524 | ??? |
| WEP_KEY_BLADE_AQ_14 | 528 | ??? |
| WEP_KEY_BLADE_AQ_15 | 529 | ??? |
| WEP_KEY_BLADE_AQ_16 | 530 | ??? |
| WEP_KEY_BLADE_AQ_17 | 531 | ??? |
| HID_NAVI_MAP_SW | 7680 | ??? |
| HID_NAVI_MAP_SB | 7681 | ??? |
| HID_NAVI_MAP_RG | 7682 | ??? |
| HID_NAVI_MAP_DC | 7683 | ??? |
| HID_NAVI_MAP_LS | 7684 | ??? |
| HID_NAVI_MAP_HE | 7685 | ??? |
| HID_NAVI_MAP_PP | 7686 | ??? |
| HID_NAVI_MAP_KG | 7687 | ??? |
| HID_NAVI_MAP_DP | 7688 | ??? |
| HID_NAVI_MAP_CD | 7689 | ??? |
| HID_REPORT_1 | 7690 | ??? |
| HID_REPORT_2 | 7691 | ??? |
| HID_REPORT_3 | 7692 | ??? |
| HID_REPORT_4 | 7693 | ??? |
| HID_REPORT_5 | 7694 | ??? |
| HID_REPORT_6 | 7695 | ??? |
| HID_REPORT_7 | 7696 | ??? |
| HID_REPORT_8 | 7697 | ??? |
| HID_REPORT_9 | 7698 | ??? |
| HID_REPORT_10 | 7699 | ??? |
| HID_REPORT_11 | 7700 | ??? |
| HID_REPORT_12 | 7701 | ??? |
| HID_REPORT_13 | 7702 | ??? |
| HID_COLLECTION_VE_0 | 7703 | ??? |
| HID_COLLECTION_VE_1 | 7704 | ??? |
| HID_COLLECTION_VE_2 | 7705 | ??? |
| HID_COLLECTION_VE_3 | 7706 | ??? |
| HID_COLLECTION_VE_4 | 7707 | ??? |
| HID_COLLECTION_VE_5 | 7708 | ??? |
| HID_COLLECTION_VE_6 | 7709 | ??? |
| HID_COLLECTION_VE_7 | 7710 | ??? |
| HID_COLLECTION_VE_8 | 7711 | ??? |
| HID_COLLECTION_VE_9 | 7712 | ??? |
| HID_COLLECTION_VE_10 | 7713 | ??? |
| HID_COLLECTION_VE_11 | 7714 | ??? |
| HID_COLLECTION_VE_12 | 7715 | ??? |
| HID_COLLECTION_VE_13 | 7716 | ??? |
| HID_COLLECTION_VE_14 | 7717 | ??? |
| HID_COLLECTION_VE_15 | 7718 | ??? |
| HID_COLLECTION_VE_16 | 7719 | ??? |
| HID_COLLECTION_VE_17 | 7720 | ??? |
| HID_COLLECTION_VE_18 | 7721 | ??? |
| HID_COLLECTION_VE_19 | 7722 | ??? |
| HID_COLLECTION_VE_20 | 7723 | ??? |
| HID_COLLECTION_VE_21 | 7724 | ??? |
| HID_COLLECTION_VE_22 | 7725 | ??? |
| HID_COLLECTION_VE_23 | 7726 | ??? |
| HID_COLLECTION_VE_24 | 7727 | ??? |
| HID_COLLECTION_VE_25 | 7728 | ??? |
| HID_COLLECTION_VE_26 | 7729 | ??? |
| HID_COLLECTION_VE_27 | 7730 | ??? |
| HID_COLLECTION_VE_28 | 7731 | ??? |
| HID_COLLECTION_VE_29 | 7732 | ??? |
| HID_COLLECTION_TE_0 | 7733 | ??? |
| HID_COLLECTION_TE_1 | 7734 | ??? |
| HID_COLLECTION_TE_2 | 7735 | ??? |
| HID_COLLECTION_TE_3 | 7736 | ??? |
| HID_COLLECTION_TE_4 | 7737 | ??? |
| HID_COLLECTION_TE_5 | 7738 | ??? |
| HID_COLLECTION_TE_6 | 7739 | ??? |
| HID_COLLECTION_TE_7 | 7740 | ??? |
| HID_COLLECTION_TE_8 | 7741 | ??? |
| HID_COLLECTION_TE_9 | 7742 | ??? |
| HID_COLLECTION_TE_10 | 7743 | ??? |
| HID_COLLECTION_TE_11 | 7744 | ??? |
| HID_COLLECTION_TE_12 | 7745 | ??? |
| HID_COLLECTION_TE_13 | 7746 | ??? |
| HID_COLLECTION_TE_14 | 7747 | ??? |
| HID_COLLECTION_TE_15 | 7748 | ??? |
| HID_COLLECTION_TE_16 | 7749 | ??? |
| HID_COLLECTION_TE_17 | 7750 | ??? |
| HID_COLLECTION_TE_18 | 7751 | ??? |
| HID_COLLECTION_TE_19 | 7752 | ??? |
| HID_COLLECTION_TE_20 | 7753 | ??? |
| HID_COLLECTION_TE_21 | 7754 | ??? |
| HID_COLLECTION_TE_22 | 7755 | ??? |
| HID_COLLECTION_TE_23 | 7756 | ??? |
| HID_COLLECTION_TE_24 | 7757 | ??? |
| HID_COLLECTION_TE_25 | 7758 | ??? |
| HID_COLLECTION_TE_26 | 7759 | ??? |
| HID_COLLECTION_TE_27 | 7760 | ??? |
| HID_COLLECTION_TE_28 | 7761 | ??? |
| HID_COLLECTION_TE_29 | 7762 | ??? |
| HID_COLLECTION_AQ_0 | 7763 | ??? |
| HID_COLLECTION_AQ_1 | 7764 | ??? |
| HID_COLLECTION_AQ_2 | 7765 | ??? |
| HID_COLLECTION_AQ_3 | 7766 | ??? |
| HID_COLLECTION_AQ_4 | 7767 | ??? |
| HID_COLLECTION_AQ_5 | 7768 | ??? |
| HID_COLLECTION_AQ_6 | 7769 | ??? |
| HID_COLLECTION_AQ_7 | 7770 | ??? |
| HID_COLLECTION_AQ_8 | 7771 | ??? |
| HID_COLLECTION_AQ_9 | 7772 | ??? |
| HID_COLLECTION_AQ_10 | 7773 | ??? |
| HID_COLLECTION_AQ_11 | 7774 | ??? |
| HID_COLLECTION_AQ_12 | 7775 | ??? |
| HID_COLLECTION_AQ_13 | 7776 | ??? |
| HID_COLLECTION_AQ_14 | 7777 | ??? |
| HID_COLLECTION_AQ_15 | 7778 | ??? |
| HID_COLLECTION_AQ_16 | 7779 | ??? |
| HID_COLLECTION_AQ_17 | 7780 | ??? |
| HID_COLLECTION_AQ_18 | 7781 | ??? |
| HID_COLLECTION_AQ_19 | 7782 | ??? |
| HID_COLLECTION_AQ_20 | 7783 | ??? |
| HID_COLLECTION_AQ_21 | 7784 | ??? |
| HID_COLLECTION_AQ_22 | 7785 | ??? |
| HID_COLLECTION_AQ_23 | 7786 | ??? |
| HID_COLLECTION_AQ_24 | 7787 | ??? |
| HID_COLLECTION_AQ_25 | 7788 | ??? |
| HID_COLLECTION_AQ_26 | 7789 | ??? |
| HID_COLLECTION_AQ_27 | 7790 | ??? |
| HID_COLLECTION_AQ_28 | 7791 | ??? |
| HID_COLLECTION_AQ_29 | 7792 | ??? |
| HID_NAVI_MAP_JB | 7793 | ??? |
| KEY_RIBBON | 7936 | ??? |
| KEY_WHITE_BUTTON | 7937 | ??? |
| KEY_PINK_CLOTH | 7938 | ??? |
| KEY_WHITE_LACE | 7939 | ??? |
| KEY_PINK_THREAD | 7940 | ??? |
| KEY_BTL_TICKET_A | 7942 | ??? |
| KEY_BTL_TICKET_B | 7943 | ??? |
| KEY_BTL_TICKET_C | 7944 | ??? |
| KEY_BTL_TICKET_D | 7945 | ??? |
| KEY_BTL_TICKET_E | 7946 | ??? |
| KEY_BTL_TICKET_F | 7947 | ??? |
| KEY_BTL_TICKET_G | 7948 | ??? |
| KEY_BTL_TICKET_H | 7949 | ??? |
| KEY_BTL_TICKET_I | 7950 | ??? |
| KEY_BTL_TICKET_J | 7951 | ??? |
| KEY_ALC_RECIPE_0 | 7952 | ??? |
| KEY_ALC_RECIPE_1 | 7953 | ??? |
| KEY_ALC_RECIPE_2 | 7954 | ??? |
| KEY_ALC_RECIPE_3 | 7955 | ??? |
| KEY_ALC_RECIPE_4 | 7956 | ??? |
| KEY_ALC_RECIPE_5 | 7957 | ??? |
| KEY_ALC_RECIPE_6 | 7958 | ??? |
| KEY_ALC_RECIPE_7 | 7959 | ??? |
| KEY_FRAGMENT_OF_STAR | 7962 | ??? |
| KEY_DISNEY_TOWN_TICKET | 7963 | ??? |
| KEY_GUARD_OF_CONNECTION | 7964 | ??? |
| KEY_GUARD_OF_CONNECTION_IM | 7965 | ??? |
| KEY_GUARD_OF_CONNECTION_A | 7967 | ??? |
| KEY_GUARD_OF_CONNECTION_T | 7968 | ??? |
| ALC_TWINKLING_CRYSTAL | 12800 | ??? |
| ALC_TIME_CRYSTAL | 12802 | ??? |
| ALC_STRONG_CRYSTAL | 12804 | ??? |
| ALC_FULL_CRYSTAL | 12806 | ??? |
| ALC_MOIST_CRYSTAL | 12808 | ??? |
| ALC_OVER_CRYSTAL | 12810 | ??? |
| ALC_AROUND_CRYSTAL | 12812 | ??? |
| ALC_CHAOS | 12814 | ??? |
| ALC_SECRET | 12815 | ??? |
| FLA_DANCE_LEMON | 17920 | ??? |
| FLA_BALLOON_MELON | 17921 | ??? |
| FLA_FANTASY_PEACH | 17922 | ??? |
| FLA_HERO_ORANGE | 17923 | ??? |
| FLA_BOTTLED_STRAWBERRY | 17925 | ??? |
| FLA_DREAMY_APPLE | 17926 | ??? |
| FLA_MELODY_GRAPE | 17927 | ??? |
| FLA_OPEN_SESAME | 17928 | ??? |
| FLA_JEWELRY_BEAN | 17929 | ??? |
| FLA_WILDE_NUTS | 17930 | ??? |
| FLA_LARGE_DROP_ALMOND | 17931 | ??? |
| FLA_MYSTERY_BEAN | 17932 | ??? |
| FLA_SECRET_RASPBERRY | 17933 | ??? |
| FLA_CRYSTAL_SUGAR | 17934 | ??? |
| FLA_MERMAID_SALT | 17935 | ??? |
| FLA_STEEPLE_PEPPER | 17936 | ??? |
| FLA_TOON_CURRY | 17937 | ??? |
| FLA_HAMMING_MINT | 17938 | ??? |
| FLA_TREASURE_HONEY | 17939 | ??? |
| FLA_ROZE_HANEY | 17940 | ??? |
| FLA_GOLD_JAM | 17941 | ??? |
| FLA_SHOOTING_STAR_SIRUP | 17942 | ??? |
| FLA_RAINBOW_SIRUP | 17943 | ??? |
| FLA_OPEN_AIR_JELLY | 17944 | ??? |
| FLA_SOFTLY_CREAM | 17946 | ??? |
| FLA_MYSTERY_CREAM | 17947 | ??? |
| FLA_SOYMILK | 17948 | ??? |
| FLA_ROMAN_MILK | 17949 | ??? |
| FLA_MOOGLE_COFFEE | 17950 | ??? |
| FLA_CRYSTAL_SODA | 17951 | ??? |
| FLA_JET_SODA | 17952 | ??? |
| FLA_ROCKET_SODA_POP | 17953 | ??? |
| FLA_GALAXY_CARAMEL | 17955 | ??? |
| FLA_VALENTINE_CHOCOLATE | 17956 | ??? |
| FLA_LIGHTNING_CANDY | 17959 | ??? |
| FLA_FLEECY_CLOUDS_CANDY | 17960 | ??? |
| FLA_FLOWER_GUMMY | 17961 | ??? |
| FLA_BIRTHDAY_CAKE | 17962 | ??? |
| FLA_WEDDING_CAKE | 17963 | ??? |
| FLA_FOREST_CASTELLA | 17964 | ??? |
| FLA_MARSHMALLOW | 17965 | ??? |
| FLA_STARRYSKY_DROP | 17966 | ??? |
| ITEM_ID_MAX | 17967 | ??? |

## FRIEND_ID

| Enum       | Value      | Description      |
|------------|---------------|---------------|
| FRIEND_PRINCE_PHILLIP_DUNGEON | 0 | ??? |
| FRIEND_PRINCE_PHILLIP_ESCAPE | 1 | ??? |
| FRIEND_PRINCE_PHILLIP_MDRAGON | 2 | ??? |
| FRIEND_CINDERELLA_THE_FIRST | 3 | ??? |
| FRIEND_CINDERELLA_THE_LATTER | 4 | ??? |
| FRIEND_JAQ | 5 | ??? |
| FRIEND_SNOWWHITE | 6 | ??? |
| FRIEND_HERCULES_POD_WEAK | 7 | ??? |
| FRIEND_HERCULES_POD_TOUGH | 8 | ??? |
| FRIEND_HERCULES_POD_TOUGH_MAX | 9 | ??? |
| FRIEND_HERCULES | 10 | ??? |
| FRIEND_MANY_ENE_HERCULES | 11 | ??? |
| FRIEND_STITCH | 12 | ??? |
| FRIEND_STITCH_GANTU | 13 | ??? |
| FRIEND_STITCH_METAMOL | 14 | ??? |
| FRIEND_ZACKS | 15 | ??? |
| FRIEND_KING | 16 | ??? |
| FRIEND_VE | 17 | ??? |
| FRIEND_AQ | 18 | ??? |
| FRIEND_TE | 19 | ??? |
| FRIEND_ID_MAX | 20 | ??? |

## ITEM_KIND

| Enum       | Value      | Description      |
|------------|---------------|---------------|
| ITEM_UNKNOWN | -1 | ??? |
| ITEM_WEAPON | 0 | ??? |
| ITEM_FLAVOR | 1 | ??? |
| ITEM_HID | 2 | ??? |
| ITEM_KEY | 3 | ??? |
| ITEM_ALCHEMY | 4 | ??? |
| ITEM_KIND_MAX | 5 | ??? |

## SHOP_ID

| Enum       | Value      | Description      |
|------------|---------------|---------------|
| SHOP_ID_NONE | 0 | ??? |
| SHOP_ID_ACCESSORIE | 1 | ??? |
| SHOP_ID_COMMAND | 2 | ??? |
| SHOP_ID_COMMAND_HOLO | 3 | ??? |
| SHOP_ID_ICE | 4 | ??? |
| SHOP_ID_MEDAL | 5 | ??? |
| _SHOP_ID_MAX | 6 | ??? |

## MISSION_KIND

| Enum       | Value      | Description      |
|------------|---------------|---------------|
| MISSION_NONE | -1 | ??? |
| DEAD_ALL | 0 | ??? |
| BOSS_DEAD | 1 | ??? |
| SERCH_MIDGET | 2 | ??? |
| ESCAPE_FOREST | 3 | ??? |
| GUARD_CINDERELLA_0 | 4 | ??? |
| GUARD_CINDERELLA_1 | 5 | ??? |
| GUARD_JAQ | 6 | ??? |
| JOINT_STRUGGLE_PHILLIP_0 | 7 | ??? |
| JOINT_STRUGGLE_PHILLIP_1 | 8 | ??? |
| BTL_MDRAGON_PHILLIP | 9 | ??? |
| BTL_VANITAS_KING | 10 | ??? |
| BTL_DEAD_ALL_KING | 11 | ??? |
| BTL_DEAD_ALL_HERCULES | 12 | ??? |
| BTL_DEAD_ALL_ZACKS_HERCULES | 13 | ??? |
| BTL_DEAD_ALL_STITCH | 14 | ??? |
| BTL_PARTS_AQ_VE | 15 | ??? |
| BTL_PARTS_VE_TE | 16 | ??? |
| BTL_PARTS_AQ_TE | 17 | ??? |
| BTL_ROCK_TITAN_HERCULES | 18 | ??? |
| BTL_METAL_STITCH | 19 | ??? |
| BTL_IRON_AYA_RAGNA | 20 | ??? |
| MINIGAME_POT_BREAK_0 | 21 | ??? |
| MINIGAME_POT_BREAK_1 | 22 | ??? |
| BTL_GUNTU_STITCH | 23 | ??? |
| MINIGAME_RIDE_BATTLE | 24 | ??? |
| PARTITION_CLOSE | 25 | ??? |
| BTL_MANY_ENEMY_HERCULES | 26 | ??? |
| BTL_MANY_ENEMY | 27 | ??? |
| FIGHT_RALLY | 28 | ??? |
| MINIGAME_RIDE_RACE_EVENT | 29 | ??? |
| MINIGAME_RIDE_RACE_A | 30 | ??? |
| MINIGAME_RIDE_RACE_B | 31 | ??? |
| MINIGAME_RIDE_RACE_C | 32 | ??? |
| MINIGAME_RIDE_BATTLE_NMAP | 33 | ??? |
| MINIGAME_RIDE_BATTLE_METAMO | 34 | ??? |
| MINIGAME_ICE_MISSION | 35 | ??? |
| MINIGAME_ICE_M1_NORMAL | 36 | ??? |
| MINIGAME_ICE_M1_MANIACK | 37 | ??? |
| MINIGAME_ICE_M2_NORMAL | 38 | ??? |
| MINIGAME_ICE_M2_MANIACK | 39 | ??? |
| MINIGAME_BALL_MISSION | 40 | ??? |
| MINIGAME_BALL_VS_DARK | 43 | ??? |
| MINIGAME_BALL_VS_DEBU | 41 | ??? |
| MINIGAME_BALL_VS_HIDE | 45 | ??? |
| MINIGAME_BALL_VS_JAST | 44 | ??? |
| MINIGAME_BALL_VS_TIP | 42 | ??? |
| MINIGAME_POT_BREAK_2 | 46 | ??? |
| BOSS_DEAD_TIMEov_or_HPxx | 47 | ??? |
| TUTORIAL_MOVE_AND_CAMERA | 50 | ??? |
| TUTORIAL_TOP | 50 | ??? |
| TUTORIAL_NORMAL_ATTACK | 51 | ??? |
| TUTORIAL_D_LINK | 52 | ??? |
| TUTORIAL_GUARD | 53 | ??? |
| TUTORIAL_CMD_GAUGE | 54 | ??? |
| TUTORIAL_SHOOT_LOCK | 55 | ??? |
| TUTORIAL_TEST_SELECT_CHARA | 56 | ??? |
| TUTORIAL_DUMMY | 57 | ??? |
| TUTORIAL_BTL_DICE | 58 | ??? |
| TUTORIAL_SAVE_POINT | 59 | ??? |
| TUTORIAL_PLAYER_SELECT | 60 | ??? |
| TUTORIAL_TEST_BTL_TERA | 61 | ??? |
| TUTORIAL_TEST_BTL_AQUA | 62 | ??? |
| TUTORIAL_TEST_BTL_VEN | 63 | ??? |
| TUTORIAL_MAX | 64 | ??? |
| BOSS_DEAD_EXT_METAMOL | 100 | ??? |
| BOSS_DEAD_EXT_VANITUS | 101 | ??? |
| BOSS_DEAD_EXT_VAN_VEN | 102 | ??? |
| BOSS_DEAD_EXT_PAN | 103 | ??? |
| BOSS_DEAD_EXT_XEA_VAN | 104 | ??? |
| BOSS_DEAD_TERA_ZEA | 105 | ??? |
| MINIGAME_ICE_M1_SPECIAL | 106 | ??? |
| MINIGAME_ICE_M2_SPECIAL | 107 | ??? |
| LIGHT_BALL | 108 | ??? |
| MINIGAME_ICE_M3_NORMAL | 109 | ??? |
| MINIGAME_ICE_M3_MANIACK | 110 | ??? |
| MINIGAME_ICE_M3_SPECIAL | 111 | ??? |
| MINIGAME_ICE_M4_NORMAL | 112 | ??? |
| MINIGAME_ICE_M4_MANIACK | 113 | ??? |
| MINIGAME_ICE_M4_SPECIAL | 114 | ??? |
| MINIGAME_ICE_M5_NORMAL | 115 | ??? |
| MINIGAME_ICE_M5_MANIACK | 116 | ??? |
| MINIGAME_ICE_M5_SPECIAL | 117 | ??? |
| MINIGAME_RIDE_RACE_D | 118 | ??? |
| FM_MISSION_ILLUSION_A | 119 | ??? |
| FM_MISSION_ILLUSION_TOP | 119 | ??? |
| FM_MISSION_ILLUSION_B | 120 | ??? |
| FM_MISSION_ILLUSION_C | 121 | ??? |
| FM_MISSION_ILLUSION_D | 122 | ??? |
| FM_MISSION_ILLUSION_E | 123 | ??? |
| FM_MISSION_ILLUSION_F | 124 | ??? |
| FM_MISSION_ILLUSION_G | 125 | ??? |
| FM_MISSION_ILLUSION_H | 126 | ??? |
| FM_MISSION_ILLUSION_I | 127 | ??? |
| FM_MISSION_ILLUSION_MAX | 127 | ??? |
| MISSION_MAX | 128 | ??? |

## OpCode

| Enum       | Value      | Description      |
|------------|---------------|---------------|
| OP_MOVE | 0 | ??? |
| OP_LOADK | 1 | ??? |
| OP_LOADBOOL | 2 | ??? |
| OP_LOADNIL | 3 | ??? |
| OP_GETUPVAL | 4 | ??? |
| OP_GETGLOBAL | 5 | ??? |
| OP_GETTABLE | 6 | ??? |
| OP_SETGLOBAL | 7 | ??? |
| OP_SETUPVAL | 8 | ??? |
| OP_SETTABLE | 9 | ??? |
| OP_NEWTABLE | 10 | ??? |
| OP_SELF | 11 | ??? |
| OP_ADD | 12 | ??? |
| OP_SUB | 13 | ??? |
| OP_MUL | 14 | ??? |
| OP_DIV | 15 | ??? |
| OP_MOD | 16 | ??? |
| OP_POW | 17 | ??? |
| OP_UNM | 18 | ??? |
| OP_NOT | 19 | ??? |
| OP_LEN | 20 | ??? |
| OP_CONCAT | 21 | ??? |
| OP_JMP | 22 | ??? |
| OP_EQ | 23 | ??? |
| OP_LT | 24 | ??? |
| OP_LE | 25 | ??? |
| OP_TEST | 26 | ??? |
| OP_TESTSET | 27 | ??? |
| OP_CALL | 28 | ??? |
| OP_TAILCALL | 29 | ??? |
| OP_RETURN | 30 | ??? |
| OP_FORLOOP | 31 | ??? |
| OP_FORPREP | 32 | ??? |
| OP_TFORLOOP | 33 | ??? |
| OP_SETLIST | 34 | ??? |
| OP_CLOSE | 35 | ??? |
| OP_CLOSURE | 36 | ??? |
| OP_VARARG | 37 | ??? |

## REFRESH_RATE

| Enum       | Value      | Description      |
|------------|---------------|---------------|
| REFRESH_RATE_60FPS | 0 | ??? |
| REFRESH_RATE_30FPS | 1 | ??? |

## CLOCK_MODE

| Enum       | Value      | Description      |
|------------|---------------|---------------|
| CLOCK_MODE_NOP | -1 | ??? |
| CLOCK_MODE_DEFAULT | 0 | ??? |
| CLOCK_MODE_222MHZ | 1 | ??? |
| CLOCK_MODE_333MHZ | 2 | ??? |

## eDataType

| Enum       | Value      | Description      |
|------------|---------------|---------------|
| TypeSByte | 0 | ??? |
| TypeByte | 1 | ??? |
| TypeShort | 2 | ??? |
| TypeUShort | 3 | ??? |
| TypeInt | 4 | ??? |
| TypeUInt | 5 | ??? |
| TypeFloat | 6 | ??? |
| TypeString | 7 | ??? |